python_drools_sdk/__init__.py
python_drools_sdk/commands/__init__.py
python_drools_sdk/commands/abstract_command.py
python_drools_sdk/commands/insert_elements_command.py
python_drools_sdk/commands/insert_object_command.py
python_drools_sdk/exceptions/__init__.py
python_drools_sdk/exceptions/drools_exception.py
python_drools_sdk/kie/__init__.py
python_drools_sdk/kie/drools.py
python_drools_sdk/utils/__init__.py
python_drools_sdk/utils/data_store.py
python_drools_sdk/utils/endpoints.py
python_drools_sdk/utils/helpers.py
python_drools_sdk/utils/make_request.py
python_drools_sdk-0.0.3.dist-info/LICENCE
python_drools_sdk-0.0.3.dist-info/METADATA
python_drools_sdk-0.0.3.dist-info/WHEEL
python_drools_sdk-0.0.3.dist-info/top_level.txt
python_drools_sdk-0.0.3.dist-info/RECORD
