Metadata-Version: 2.1
Name: python-drools-sdk
Version: 0.0.3
Summary: A Drools KIE SERVER client library
Home-page: https://github.com/PapiHack/python-drools-sdk
Author: PapiHack
Author-email: mssmbaye@gmail.com
License: UNKNOWN
Project-URL: Bug Tracker, https://github.com/PapiHack/python-drools-sdk/issues
Keywords: python,drools,kie-server,python drools sdk,python kie-server client,python drools client
Platform: UNKNOWN
Classifier: Programming Language :: Python :: 3
Classifier: License :: OSI Approved :: MIT License
Classifier: Operating System :: OS Independent
Requires-Python: >=3.6
License-File: LICENCE
Requires-Dist: certifi (==2021.10.8)
Requires-Dist: charset-normalizer (==2.0.6)
Requires-Dist: idna (==3.2)
Requires-Dist: jsons (==1.5.1)
Requires-Dist: requests (==2.26.0)
Requires-Dist: typish (==1.9.3)
Requires-Dist: urllib3 (==1.26.7)
